project_code/__init__.py
project_code/script.py
kritika_api2-0.1.dist-info/License.txt
kritika_api2-0.1.dist-info/METADATA
kritika_api2-0.1.dist-info/WHEEL
kritika_api2-0.1.dist-info/top_level.txt
kritika_api2-0.1.dist-info/RECORD
